gximagecomputing/RenderGRFF.cpython-311-i386-linux-gnu.so
gximagecomputing/radio.py
gximagecomputing/__init__.py
gximagecomputing.libs/libgomp-65f46eca.so.1.0.0
gximagecomputing-0.0.1.dist-info/METADATA
gximagecomputing-0.0.1.dist-info/top_level.txt
gximagecomputing-0.0.1.dist-info/RECORD
gximagecomputing-0.0.1.dist-info/WHEEL
