Metadata-Version: 2.1
Name: gximagecomputing
Version: 0.0.1
Summary: This code computes the 2D maps of the solar gyroresonance and free-free microwave emission using the models of active regions created by the GX Simulator.
Author-email: Alexey Kuznetsov <test@example.com>
Maintainer-email: Alexey Kuznetsov <test@example.com>
Project-URL: Issues, https://github.com/kuznetsov-radio/gximagecomputing/issues
Project-URL: Repository, https://github.com/kuznetsov-radio/gximagecomputing/
Keywords: Sun,radio emission,gyroresonance,microwave emission,Sun active regions
Classifier: Development Status :: 3 - Alpha
Classifier: Intended Audience :: Science/Research
Classifier: Programming Language :: Python :: 3
Classifier: Programming Language :: Python :: 3.10
Classifier: Programming Language :: Python :: 3.11
Classifier: Programming Language :: Python :: 3.12
Requires-Dist: numpy
Requires-Dist: astropy
Requires-Dist: sunpy
Requires-Dist: scipy
Requires-Dist: importlib-metadata; python_version >= "3.10"
